responder_login/__about__.py
responder_login/__init__.py
responder_login/config.py
responder_login/decorators.py
responder_login/default_callbacks.py
responder_login/login_manager.py
responder_login/mixins.py
Responder_Login-0.0.8.dist-info/LICENSE
Responder_Login-0.0.8.dist-info/METADATA
Responder_Login-0.0.8.dist-info/WHEEL
Responder_Login-0.0.8.dist-info/top_level.txt
Responder_Login-0.0.8.dist-info/RECORD
